ngtools/__init__.py
ngtools/_version.py
ngtools/cmdata.py
ngtools/dandifs.py
ngtools/datasources.py
ngtools/layers.py
ngtools/opener.py
ngtools/protocols.py
ngtools/scene.py
ngtools/shaders.py
ngtools/spaces.py
ngtools/transforms.py
ngtools/typing.py
ngtools/units.py
ngtools/utils.py
ngtools/_lta/__init__.py
ngtools/_lta/basis.py
ngtools/_lta/conversions.py
ngtools/_lta/expm.py
ngtools/_lta/fsutils.py
ngtools/_lta/layout.py
ngtools/_lta/lie.py
ngtools/_lta/lta.py
ngtools/_lta/utils.py
ngtools/local/__init__.py
ngtools/local/cli.py
ngtools/local/console.py
ngtools/local/datasources.py
ngtools/local/fileserver.py
ngtools/local/handlers.py
ngtools/local/iostream.py
ngtools/local/termcolors.py
ngtools/local/tracts.py
ngtools/local/viewer.py
ngtools/schemas/__init__.py
ngtools/tests/__init__.py
ngtools/tests/test_spaces.py
ngtools/tests/test_transforms.py
ngtools-0.1.6.dist-info/licenses/LICENSE
ngtools-0.1.6.dist-info/METADATA
ngtools-0.1.6.dist-info/WHEEL
ngtools-0.1.6.dist-info/entry_points.txt
ngtools-0.1.6.dist-info/top_level.txt
ngtools-0.1.6.dist-info/RECORD
