Metadata-Version: 2.4
Name: ngtools
Version: 0.1.6
Summary: Build and manipulate Neuroglancer scenes
Author-email: Yael Balbastre <y.balbastre@ucl.ac.uk>
Maintainer-email: Yael Balbastre <y.balbastre@ucl.ac.uk>
License: MIT License
Project-URL: Homepage, https://github.com/balbasty/ngtools
Project-URL: Issues, https://github.com/balbasty/ngtools/issues
Classifier: License :: OSI Approved :: MIT License
Classifier: Operating System :: OS Independent
Classifier: Programming Language :: Python :: 3
Classifier: Intended Audience :: Science/Research
Classifier: Topic :: Scientific/Engineering :: Medical Science Apps.
Classifier: Topic :: Scientific/Engineering :: Visualization
Requires-Python: >=3.10
License-File: LICENSE
Requires-Dist: neuroglancer
Requires-Dist: numpy>=1.20
Requires-Dist: dask
Requires-Dist: fsspec[full]>=2021.0.0
Requires-Dist: cryptography>=36.0.2
Requires-Dist: universal_pathlib
Requires-Dist: nibabel
Requires-Dist: nitransforms>=22.0
Requires-Dist: tifffile
Requires-Dist: zarr
Requires-Dist: indexed_gzip
Requires-Dist: cloud-volume
Requires-Dist: dandi>=0.44
Requires-Dist: requests
Dynamic: license-file
